{
    "id": "pbc_2963937958",
    "listRule": "",
    "viewRule": "",
    "createRule": "true = @request.auth.isAdmin",
    "updateRule": "true = @request.auth.isAdmin",
    "deleteRule": "true = @request.auth.isAdmin",
    "name": "mentor",
    "type": "base",
    "fields": [
        {
            "autogeneratePattern": "[a-z0-9]{15}",
            "hidden": false,
            "id": "text3208210256",
            "max": 15,
            "min": 15,
            "name": "id",
            "pattern": "^[a-z0-9]+$",
            "presentable": false,
            "primaryKey": true,
            "required": true,
            "system": true,
            "type": "text"
        },
        {
            "autogeneratePattern": "",
            "hidden": false,
            "id": "text1579384326",
            "max": 0,
            "min": 0,
            "name": "name",
            "pattern": "",
            "presentable": false,
            "primaryKey": false,
            "required": false,
            "system": false,
            "type": "text"
        },
        {
            "autogeneratePattern": "",
            "hidden": false,
            "id": "text2665083498",
            "max": 0,
            "min": 0,
            "name": "specialization",
            "pattern": "",
            "presentable": false,
            "primaryKey": false,
            "required": false,
            "system": false,
            "type": "text"
        },
        {
            "autogeneratePattern": "",
            "hidden": false,
            "id": "text3885137012",
            "max": 0,
            "min": 0,
            "name": "email",
            "pattern": "",
            "presentable": false,
            "primaryKey": false,
            "required": false,
            "system": false,
            "type": "text"
        },
        {
            "hidden": false,
            "id": "file3309110367",
            "maxSelect": 1,
            "maxSize": 0,
            "mimeTypes": [],
            "name": "image",
            "presentable": false,
            "protected": false,
            "required": false,
            "system": false,
            "thumbs": [],
            "type": "file"
        },
        {
            "hidden": false,
            "id": "bool2323052248",
            "name": "isActive",
            "presentable": false,
            "required": false,
            "system": false,
            "type": "bool"
        },
        {
            "cascadeDelete": false,
            "collectionId": "pbc_2090534506",
            "hidden": false,
            "id": "relation1874629670",
            "maxSelect": 999,
            "minSelect": 0,
            "name": "tags",
            "presentable": false,
            "required": false,
            "system": false,
            "type": "relation"
        },
        {
            "hidden": false,
            "id": "select2726737987",
            "maxSelect": 7,
            "name": "dayAvail",
            "presentable": false,
            "required": false,
            "system": false,
            "type": "select",
            "values": [
                "Monday",
                "Tuesday",
                "Wednesday",
                "Thursday",
                "Friday",
                "Saturday",
                "Sunday"
            ]
        },
        {
            "autogeneratePattern": "",
            "hidden": false,
            "id": "text1240542687",
            "max": 0,
            "min": 0,
            "name": "startTimeActive",
            "pattern": "",
            "presentable": false,
            "primaryKey": false,
            "required": false,
            "system": false,
            "type": "text"
        },
        {
            "autogeneratePattern": "",
            "hidden": false,
            "id": "text317319697",
            "max": 0,
            "min": 0,
            "name": "endTimeActive",
            "pattern": "",
            "presentable": false,
            "primaryKey": false,
            "required": false,
            "system": false,
            "type": "text"
        },
        {
            "hidden": false,
            "id": "autodate2990389176",
            "name": "created",
            "onCreate": true,
            "onUpdate": false,
            "presentable": false,
            "system": false,
            "type": "autodate"
        },
        {
            "hidden": false,
            "id": "autodate3332085495",
            "name": "updated",
            "onCreate": true,
            "onUpdate": true,
            "presentable": false,
            "system": false,
            "type": "autodate"
        }
    ],
    "indexes": [],
    "created": "2026-02-25 21:34:46.879Z",
    "updated": "2026-03-02 17:31:50.737Z",
    "system": false
}